[{"slug": "阳光时尚杂志拼贴画-1_0bba02", "title_zh": "阳光时尚杂志拼贴画", "title_en": "阳光时尚杂志拼贴画", "category_slug": "character", "category_name_zh": "角色人物", "tags": ["character"], "primary_image": {"r2AccountId": null, "r2Key": null, "remoteUrl": "https://cms-assets.youmind.com/media/1780045817911_1wh5fh_HJbH311awAAAZt-.jpg", "width": null, "height": null, "lqip": null}, "view_count": 1, "like_count": 0, "created_at": ""}, {"slug": "室内设计-电视背景墙-客厅设计-7_221371", "title_zh": "室内设计、电视背景墙、客厅设计", "title_en": "室内设计、电视背景墙、客厅设计", "category_slug": "architecture_interior", "category_name_zh": "建筑室内", "tags": ["室内设计", "architecture", "空间场景", "photography", "portrait"], "primary_image": {"r2AccountId": null, "r2Key": null, "remoteUrl": "https://liblibai-online.liblib.cloud/img/1544180259934af6bc00fed12343a5cd/d968dd8e748f906484ad2ad079df98bb39c02ad27457c7064da7ed4f4fa28fc1.png", "width": null, "height": null, "lqip": null}, "view_count": 0, "like_count": 0, "created_at": ""}, {"slug": "视觉小说废弃路线-ui-0_9188d0", "title_zh": "视觉小说废弃路线 UI", "title_en": "视觉小说废弃路线 UI", "category_slug": "branding_visual", "category_name_zh": "品牌视觉", "tags": ["novel", "branding", "ui"], "primary_image": {"r2AccountId": null, "r2Key": null, "remoteUrl": "https://cms-assets.youmind.com/media/1777711058997_fxxave_HHO33j8bUAAP1L9.jpg", "width": null, "height": null, "lqip": null}, "view_count": 0, "like_count": 0, "created_at": ""}, {"slug": "liblib-建筑及室内设计-2f0fc3ba-8_8240c2", "title_zh": "Liblib 建筑及室内设计 2f0fc3ba", "title_en": "Liblib 建筑及室内设计 2f0fc3ba", "category_slug": "architecture_interior", "category_name_zh": "建筑室内", "tags": ["architecture", "illustration", "landscape"], "primary_image": {"r2AccountId": null, "r2Key": null, "remoteUrl": "https://liblibai-online.liblib.cloud/img/579fc2af5940427f99a318f39d6ea2d3/2091fe2f-a8c3-4e78-9d28-a9a1bfeb5cd2.png", "width": null, "height": null, "lqip": null}, "view_count": 0, "like_count": 0, "created_at": ""}, {"slug": "liblib-动漫游戏-3c34f07c-9_0e557b", "title_zh": "Liblib 动漫游戏 3c34f07c", "title_en": "Liblib 动漫游戏 3c34f07c", "category_slug": "anime_game", "category_name_zh": "动漫游戏", "tags": ["anime", "fantasy"], "primary_image": {"r2AccountId": null, "r2Key": null, "remoteUrl": "https://liblibai-online.liblib.cloud/community-img/696937329-7a0778f41fb4d77c58d90104d725c01a63d4e0057e75175976eb520fe816aee0.png", "width": null, "height": null, "lqip": null}, "view_count": 0, "like_count": 0, "created_at": ""}, {"slug": "日本法律服务lp横幅设计-律所税务师事务所广告banner-4_570d78", "title_zh": "日本法律服务LP横幅设计｜律所税务师事务所广告Banner", "title_en": "日本法律服务LP横幅设计｜律所税务师事务所广告Banner", "category_slug": "ecommerce", "category_name_zh": "电商营销", "tags": ["日本法律服务", "lp横幅", "广告设计", "广告创意", "creative-play", "ecommerce", "律师事务所广告"], "primary_image": {"r2AccountId": null, "r2Key": null, "remoteUrl": "https://static.prompthub.xin/uploads/prompts/1777215907541-8b6cfd38781da253284f0577ff3179c8_detail.jpg?auth_key=1777949834-0-0-3571b0ee6d9bde604f4ae621243f73db", "width": null, "height": null, "lqip": null}, "view_count": 0, "like_count": 0, "created_at": ""}, {"slug": "liblib-风格插画-f80abf9f-6_fba385", "title_zh": "Liblib 风格插画 f80abf9f", "title_en": "Liblib 风格插画 f80abf9f", "category_slug": "branding_visual", "category_name_zh": "品牌视觉", "tags": ["architecture", "illustration", "branding"], "primary_image": {"r2AccountId": null, "r2Key": null, "remoteUrl": "https://liblibai-online.liblib.cloud/img/f751f89354ef4287a32642591115eb66/1d499ce4e0e09d9bbb9c39f5b936a98542fdc8582f5a89ee7e902b20b379e68c.png", "width": null, "height": null, "lqip": null}, "view_count": 0, "like_count": 0, "created_at": ""}, {"slug": "q版卡通角色-5_454936", "title_zh": "Q版卡通角色", "title_en": "Q版卡通角色", "category_slug": "creative_play", "category_name_zh": "创意玩法", "tags": ["anime", "creative-play"], "primary_image": {"r2AccountId": null, "r2Key": null, "remoteUrl": "https://liblibai-online.liblib.cloud/community-img/681790482-ce7801fa09580890d327d153d5e2ca1477ee7e498755cc1b3c2c6c313c589f38.png", "width": null, "height": null, "lqip": null}, "view_count": 0, "like_count": 0, "created_at": ""}, {"slug": "等距视角办公人员素材表-9_3ecfd5", "title_zh": "等距视角办公人员素材表", "title_en": "等距视角办公人员素材表", "category_slug": "other", "category_name_zh": "其他", "tags": ["other"], "primary_image": {"r2AccountId": null, "r2Key": null, "remoteUrl": "https://cms-assets.youmind.com/media/1778491001278_hseab6_HHg2cataIAAdKnF.jpg", "width": null, "height": null, "lqip": null}, "view_count": 0, "like_count": 0, "created_at": ""}, {"slug": "动漫少女破屏而出-5_472e88", "title_zh": "动漫少女破屏而出", "title_en": "动漫少女破屏而出", "category_slug": "anime_game", "category_name_zh": "动漫游戏", "tags": ["anime"], "primary_image": {"r2AccountId": null, "r2Key": null, "remoteUrl": "https://cms-assets.youmind.com/media/1778230129688_42mdzo_HHrxkfKaMAAW3Tj.jpg", "width": null, "height": null, "lqip": null}, "view_count": 0, "like_count": 0, "created_at": ""}, {"slug": "日本生态社区品牌宣传海报设计提示词-6_baf0ad", "title_zh": "日本生态社区品牌宣传海报设计提示词", "title_en": "日本生态社区品牌宣传海报设计提示词", "category_slug": "branding_visual", "category_name_zh": "品牌视觉", "tags": ["生态社区", "poster", "branding", "poster-design", "日式美学"], "primary_image": {"r2AccountId": null, "r2Key": null, "remoteUrl": "https://static.prompthub.xin/uploads/prompts/1777285796697-219059f4413e791ac23f48a8ff10ae4e_detail.jpg?auth_key=1777949769-0-0-904f1013126a32b69e6e736b08c8e4dd", "width": null, "height": null, "lqip": null}, "view_count": 0, "like_count": 0, "created_at": ""}, {"slug": "q版彩线角色-0_84952d", "title_zh": "Q版彩线角色", "title_en": "Q版彩线角色", "category_slug": "creative_play", "category_name_zh": "创意玩法", "tags": ["creative-play"], "primary_image": {"r2AccountId": null, "r2Key": null, "remoteUrl": "https://liblibai-online.liblib.cloud/img/12d30665cbbc8b3fa3cf163216704f26/34b4d7d706f507df429761d65ad5d34e76686d9bad8e902684a148586b016e71.png", "width": null, "height": null, "lqip": null}, "view_count": 0, "like_count": 0, "created_at": ""}, {"slug": "未来感玻璃-ui-宣传横幅-7_27c840", "title_zh": "未来感玻璃 UI 宣传横幅", "title_en": "未来感玻璃 UI 宣传横幅", "category_slug": "graphic_design", "category_name_zh": "平面设计", "tags": ["graphic-design", "ui"], "primary_image": {"r2AccountId": null, "r2Key": null, "remoteUrl": "https://cms-assets.youmind.com/media/1778662267398_55pq1n_HICaWrIakAA0QRS.jpg", "width": null, "height": null, "lqip": null}, "view_count": 0, "like_count": 0, "created_at": ""}, {"slug": "liblib-动漫游戏-7d16ca06-1_9dd391", "title_zh": "Liblib 动漫游戏 7d16ca06", "title_en": "Liblib 动漫游戏 7d16ca06", "category_slug": "anime_game", "category_name_zh": "动漫游戏", "tags": ["architecture", "anime", "游戏设计", "空间场景", "fantasy"], "primary_image": {"r2AccountId": null, "r2Key": null, "remoteUrl": "https://liblibai-online.liblib.cloud/community-img/331048308-84b6f39b0d412885ef4d63f6ab47d07fa4b6e49dde3886d8ff11587cec0fdedf.png", "width": null, "height": null, "lqip": null}, "view_count": 0, "like_count": 0, "created_at": ""}, {"slug": "liblib-风格插画-24ce14ff-1_25ceb8", "title_zh": "Liblib 风格插画 24ce14ff", "title_en": "Liblib 风格插画 24ce14ff", "category_slug": "illustration", "category_name_zh": "风格插画", "tags": ["illustration"], "primary_image": {"r2AccountId": null, "r2Key": null, "remoteUrl": "https://liblibai-online.liblib.cloud/img/745e1de4f491455cbf7a200159ff2196/29b3ea70-a6a4-49bd-86c6-b84b047cf0ff.png", "width": null, "height": null, "lqip": null}, "view_count": 0, "like_count": 0, "created_at": ""}, {"slug": "liblib-创意玩法-11dc8254-f_ea836a", "title_zh": "Liblib 创意玩法 11dc8254", "title_en": "Liblib 创意玩法 11dc8254", "category_slug": "creative_play", "category_name_zh": "创意玩法", "tags": ["creative-play"], "primary_image": {"r2AccountId": null, "r2Key": null, "remoteUrl": "https://liblibai-online.liblib.cloud/community-img/genius_playground/image/10f43772ef194fbda818c96f85af92b8/5a6b45964088c3143c3b926afc827f46cc454725fb279b8b9abf1429f416fb7e.png", "width": null, "height": null, "lqip": null}, "view_count": 0, "like_count": 0, "created_at": ""}, {"slug": "日本美妆广告宣传车-1_192c9a", "title_zh": "日本美妆广告宣传车", "title_en": "日本美妆广告宣传车", "category_slug": "ecommerce", "category_name_zh": "电商营销", "tags": ["ecommerce"], "primary_image": {"r2AccountId": null, "r2Key": null, "remoteUrl": "https://cms-assets.youmind.com/media/1779096684951_d1zwok_HIQd3flbwAEjfuS.jpg", "width": null, "height": null, "lqip": null}, "view_count": 0, "like_count": 0, "created_at": ""}, {"slug": "ip品牌logo字体-现代简约活动标题字体-中国速度-e_6dca8f", "title_zh": "IP品牌logo字体，现代简约活动标题字体《中国速度》", "title_en": "IP品牌logo字体，现代简约活动标题字体《中国速度》", "category_slug": "graphic_design", "category_name_zh": "平面设计", "tags": ["branding", "logo", "typography", "graphic-design"], "primary_image": {"r2AccountId": null, "r2Key": null, "remoteUrl": "https://liblibai-online.liblib.cloud/community-img/600099608-986bc1a1ece2196740f28730b2bda0b5b7b031af09542ccc43574da56792fb76.png", "width": null, "height": null, "lqip": null}, "view_count": 0, "like_count": 0, "created_at": ""}, {"slug": "复古欧洲旅行写生本-6_417853", "title_zh": "复古欧洲旅行写生本", "title_en": "复古欧洲旅行写生本", "category_slug": "branding_visual", "category_name_zh": "品牌视觉", "tags": ["branding"], "primary_image": {"r2AccountId": null, "r2Key": null, "remoteUrl": "https://cms-assets.youmind.com/media/1778835861635_w81vc8_HIRIQccbAAArHUf.jpg", "width": null, "height": null, "lqip": null}, "view_count": 0, "like_count": 0, "created_at": ""}, {"slug": "liblib-文创周边-7a8fc77e-1_cb5127", "title_zh": "Liblib 文创周边 7a8fc77e", "title_en": "Liblib 文创周边 7a8fc77e", "category_slug": "cultural_products", "category_name_zh": "文创周边", "tags": ["cultural-goods"], "primary_image": {"r2AccountId": null, "r2Key": null, "remoteUrl": "https://liblibai-online.liblib.cloud/community-img/737337638-c129b8f50a1b9207577b0ab85a37b1f20a1d74c388afa2c45fd7b479248815d1.png", "width": null, "height": null, "lqip": null}, "view_count": 0, "like_count": 0, "created_at": ""}]