[{"slug": "都市街头潮流生活方式商业摄影-1_d859ae", "title_zh": "都市街头潮流生活方式商业摄影", "title_en": "都市街头潮流生活方式商业摄影", "category_slug": "photography", "category_name_zh": "摄影写真", "tags": ["photography"], "primary_image": {"r2AccountId": null, "r2Key": null, "remoteUrl": "https://cms-assets.youmind.com/media/1777539298146_v771t1_HHDMrpkbsAA-M29.jpg", "width": null, "height": null, "lqip": null}, "view_count": 0, "like_count": 0, "created_at": ""}, {"slug": "z-image情绪氛围感-胶片颗粒-d_f85623", "title_zh": "Z-Image情绪氛围感，胶片颗粒", "title_en": "Z-Image情绪氛围感，胶片颗粒", "category_slug": "photography", "category_name_zh": "摄影写真", "tags": ["photography", "portrait"], "primary_image": {"r2AccountId": null, "r2Key": null, "remoteUrl": "https://liblibai-online.liblib.cloud/community-img/679747466-041113af1e71e5f6b1f87f7d4d9d1770359a8a65081e97d59ad8be475dc6bacc.png", "width": null, "height": null, "lqip": null}, "view_count": 0, "like_count": 0, "created_at": ""}, {"slug": "rainbow-pop-idol-manga-transformation-2_32c286", "title_zh": "Rainbow Pop Idol Manga Transformation", "title_en": "Rainbow Pop Idol Manga Transformation", "category_slug": "other", "category_name_zh": "其他", "tags": ["other"], "primary_image": {"r2AccountId": null, "r2Key": null, "remoteUrl": "https://cms-assets.youmind.com/media/1777884824096_xbtu7p_HHXtkivaQAAw1U7.jpg", "width": null, "height": null, "lqip": null}, "view_count": 0, "like_count": 0, "created_at": ""}, {"slug": "b端ui素材丨图标网页科技元素-d_34e3da", "title_zh": "B端UI素材丨图标网页科技元素", "title_en": "B端UI素材丨图标网页科技元素", "category_slug": "graphic_design", "category_name_zh": "平面设计", "tags": ["product", "anime", "branding", "tech-scifi", "fantasy", "logo", "graphic-design", "ui"], "primary_image": {"r2AccountId": null, "r2Key": null, "remoteUrl": "https://liblibai-online.liblib.cloud/img/7f2308dc89df4e64a17a6bb5a6c1af3b/83de9fda20db80407518d18e85bb58f52670a546160a5fb2986f54d738c819fa.png", "width": null, "height": null, "lqip": null}, "view_count": 0, "like_count": 0, "created_at": ""}, {"slug": "liblib-建筑及室内设计-b42e9803-5_7024a9", "title_zh": "Liblib 建筑及室内设计 b42e9803", "title_en": "Liblib 建筑及室内设计 b42e9803", "category_slug": "architecture_interior", "category_name_zh": "建筑室内", "tags": ["architecture"], "primary_image": {"r2AccountId": null, "r2Key": null, "remoteUrl": "https://liblibai-online.liblib.cloud/community-img/678506868-2bfaeb84e6d34282ef6aa96c3ef1e8e32489830db9eb9d8ac84e2c9afaa79582.png", "width": null, "height": null, "lqip": null}, "view_count": 0, "like_count": 0, "created_at": ""}, {"slug": "liblib-建筑及室内设计-8f533fb5-a_607a09", "title_zh": "Liblib 建筑及室内设计 8f533fb5", "title_en": "Liblib 建筑及室内设计 8f533fb5", "category_slug": "architecture_interior", "category_name_zh": "建筑室内", "tags": ["architecture"], "primary_image": {"r2AccountId": null, "r2Key": null, "remoteUrl": "https://liblibai-online.liblib.cloud/community-img/259bf4eab7ed0df5f4ec822ff146fdf373dd12c911367517641a5a1eff1e7347.png", "width": null, "height": null, "lqip": null}, "view_count": 0, "like_count": 0, "created_at": ""}, {"slug": "pipi-il-cg5-3-d_efb23f", "title_zh": "pipi-iL-CG5.3", "title_en": "pipi-iL-CG5.3", "category_slug": "novel_story", "category_name_zh": "小说推文", "tags": ["novel"], "primary_image": {"r2AccountId": null, "r2Key": null, "remoteUrl": "https://liblibai-online.liblib.cloud/img/5dc0164a2dba4c38a7cd0e0e9c9ed1d2/d2f387ab035a54cc287475d8be5089817c547454e773f5c7773da9db51a2215f.png", "width": null, "height": null, "lqip": null}, "view_count": 0, "like_count": 0, "created_at": ""}, {"slug": "liblib-小说推文-a869b7a6-4_ba33c4", "title_zh": "Liblib 小说推文 a869b7a6", "title_en": "Liblib 小说推文 a869b7a6", "category_slug": "novel_story", "category_name_zh": "小说推文", "tags": ["novel"], "primary_image": {"r2AccountId": null, "r2Key": null, "remoteUrl": "https://liblibai-online.liblib.cloud/sd-gen-save-img/647177935-95845dfc6be851b9fa513552aa30197753a3b36d6fd5e39014fa5bef4a317340.png", "width": null, "height": null, "lqip": null}, "view_count": 0, "like_count": 0, "created_at": ""}, {"slug": "中国草书书法卷轴-宋韵墨宝生成器-8_74feac", "title_zh": "中国草书书法卷轴 · 宋韵墨宝生成器", "title_en": "中国草书书法卷轴 · 宋韵墨宝生成器", "category_slug": "illustration", "category_name_zh": "风格插画", "tags": ["illustration", "中国草书", "书法卷轴", "宣纸", "guofeng", "宋代美学"], "primary_image": {"r2AccountId": null, "r2Key": null, "remoteUrl": "https://static.prompthub.xin/uploads/prompts/1777283359097-f4297039b1bb164e78efa9ddc59b0581_detail.jpg?auth_key=1777949710-0-0-5d1ad0c7025422d12d5acbc04523c2d5", "width": null, "height": null, "lqip": null}, "view_count": 0, "like_count": 0, "created_at": ""}, {"slug": "外星冰雪世界中的电影感宇航员-7_369adc", "title_zh": "外星冰雪世界中的电影感宇航员", "title_en": "外星冰雪世界中的电影感宇航员", "category_slug": "other", "category_name_zh": "其他", "tags": ["other"], "primary_image": {"r2AccountId": null, "r2Key": null, "remoteUrl": "https://cms-assets.youmind.com/media/1779008334252_gtrqmk_HIdstwcasAA79tm.jpg", "width": null, "height": null, "lqip": null}, "view_count": 0, "like_count": 0, "created_at": ""}, {"slug": "角色记忆相册-0_3a2395", "title_zh": "角色记忆相册", "title_en": "角色记忆相册", "category_slug": "character", "category_name_zh": "角色人物", "tags": ["character"], "primary_image": {"r2AccountId": null, "r2Key": null, "remoteUrl": "https://cms-assets.youmind.com/media/1780735273102_w7tpd9_HKETwRSasAA26s4.jpg", "width": null, "height": null, "lqip": null}, "view_count": 0, "like_count": 0, "created_at": ""}, {"slug": "liblib-风格插画-25ce0781-d_a19fde", "title_zh": "Liblib 风格插画 25ce0781", "title_en": "Liblib 风格插画 25ce0781", "category_slug": "illustration", "category_name_zh": "风格插画", "tags": ["illustration"], "primary_image": {"r2AccountId": null, "r2Key": null, "remoteUrl": "https://liblibai-online.liblib.cloud/img/83bc4e0efd644dc68e349125b6456f4a/87aeb351-a745-482f-ad6b-9037cf74db5d.png", "width": null, "height": null, "lqip": null}, "view_count": 0, "like_count": 0, "created_at": ""}, {"slug": "liblib-动漫游戏-207ad4b3-8_da3a58", "title_zh": "Liblib 动漫游戏 207ad4b3", "title_en": "Liblib 动漫游戏 207ad4b3", "category_slug": "anime_game", "category_name_zh": "动漫游戏", "tags": ["anime", "fantasy"], "primary_image": {"r2AccountId": null, "r2Key": null, "remoteUrl": "https://liblibai-online.liblib.cloud/community-img/7fa446b748b3532f1d03e57484d3a4e92585c51eb8ac9e0005f639f090db3935.png", "width": null, "height": null, "lqip": null}, "view_count": 0, "like_count": 0, "created_at": ""}, {"slug": "奢华香水广告人像-6_713ecc", "title_zh": "奢华香水广告人像", "title_en": "奢华香水广告人像", "category_slug": "photography", "category_name_zh": "摄影写真", "tags": ["photography", "portrait"], "primary_image": {"r2AccountId": null, "r2Key": null, "remoteUrl": "https://cms-assets.youmind.com/media/1777797560310_x3fmsk_HHU6-fjWAAAKVLa.jpg", "width": null, "height": null, "lqip": null}, "view_count": 0, "like_count": 0, "created_at": ""}, {"slug": "龙凤-锦鲤-纹样-b_2a0c1f", "title_zh": "龙凤 锦鲤 纹样", "title_en": "龙凤 锦鲤 纹样", "category_slug": "illustration", "category_name_zh": "风格插画", "tags": ["illustration"], "primary_image": {"r2AccountId": null, "r2Key": null, "remoteUrl": "https://liblibai-online.liblib.cloud/train/sample_images/0f69cf31aa4c4daf4173d388ad4d6366992705b34ebdc341abf53d7233397ab2.jpg", "width": null, "height": null, "lqip": null}, "view_count": 0, "like_count": 0, "created_at": ""}, {"slug": "卡片-9_d10d28", "title_zh": "卡片", "title_en": "卡片", "category_slug": "cultural_products", "category_name_zh": "文创周边", "tags": ["cultural-goods"], "primary_image": {"r2AccountId": null, "r2Key": null, "remoteUrl": "https://liblibai-online.liblib.cloud/img/745e1de4f491455cbf7a200159ff2196/2b1ee830-1360-447a-aa8b-1c03239c0925.png", "width": null, "height": null, "lqip": null}, "view_count": 0, "like_count": 0, "created_at": ""}, {"slug": "敦煌飞天主题壁画-2_ee6d07", "title_zh": "敦煌飞天主题壁画", "title_en": "敦煌飞天主题壁画", "category_slug": "illustration", "category_name_zh": "风格插画", "tags": ["illustration"], "primary_image": {"r2AccountId": null, "r2Key": null, "remoteUrl": "https://liblibai-online.liblib.cloud/img/9f462ad052d0457c9689ecff38a82cd7/95c0bddbf3761886dda68afb39f4f3e8b00ade1e2567d00a99dcd2ce5c566259.png", "width": null, "height": null, "lqip": null}, "view_count": 0, "like_count": 0, "created_at": ""}, {"slug": "剪纸风格-7_8ea3b1", "title_zh": "剪纸风格", "title_en": "剪纸风格", "category_slug": "architecture_interior", "category_name_zh": "建筑室内", "tags": ["architecture", "剪纸风格"], "primary_image": {"r2AccountId": null, "r2Key": null, "remoteUrl": "https://liblibai-online.liblib.cloud/img/b934ab1678ca4a6e94cd451e9042ab46/05bddce2df077b0e236d61a0ecbb12f693b987ebf6cf27b858236ddeebcb2530.png", "width": null, "height": null, "lqip": null}, "view_count": 0, "like_count": 0, "created_at": ""}, {"slug": "liblib-建筑及室内设计-fc1f7b38-d_71f523", "title_zh": "Liblib 建筑及室内设计 fc1f7b38", "title_en": "Liblib 建筑及室内设计 fc1f7b38", "category_slug": "architecture_interior", "category_name_zh": "建筑室内", "tags": ["architecture"], "primary_image": {"r2AccountId": null, "r2Key": null, "remoteUrl": "https://liblibai-online.liblib.cloud/community-img/258529252-a37614cdac4039fda9af23724223ea366a0faa0326157150361bbb51f1eb8a4d.png", "width": null, "height": null, "lqip": null}, "view_count": 0, "like_count": 0, "created_at": ""}, {"slug": "餐厅设计-3_9f7d5d", "title_zh": "餐厅设计", "title_en": "餐厅设计", "category_slug": "architecture_interior", "category_name_zh": "建筑室内", "tags": ["architecture"], "primary_image": {"r2AccountId": null, "r2Key": null, "remoteUrl": "https://liblibai-online.liblib.cloud/community-img/711729429-200fc19e82ee195b0def027a938d3917c4a2f6b79e363a1bdf7a6fe5ce682ab1.png", "width": null, "height": null, "lqip": null}, "view_count": 0, "like_count": 0, "created_at": ""}]