[{"slug": "水墨-e_99e6a0", "title_zh": "水墨", "title_en": "水墨", "category_slug": "architecture_interior", "category_name_zh": "建筑室内", "tags": ["cartoon", "architecture", "illustration", "anime", "场景"], "primary_image": {"r2AccountId": null, "r2Key": null, "remoteUrl": "https://liblibai-online.liblib.cloud/sd-images/cdb130a5a81d45b59ca86c09d3992e24336aec7ca09eefdf3cf71e410ef6e769.png", "width": null, "height": null, "lqip": null}, "view_count": 0, "like_count": 0, "created_at": ""}, {"slug": "dark-ai-chat-4k-图像放大教程-1_676ec8", "title_zh": "Dark AI Chat 4K 图像放大教程", "title_en": "Dark AI Chat 4K 图像放大教程", "category_slug": "other", "category_name_zh": "其他", "tags": ["other"], "primary_image": {"r2AccountId": null, "r2Key": null, "remoteUrl": "https://cms-assets.youmind.com/media/1779612425334_n176kq_HI-WQu1akAAljqY.png", "width": null, "height": null, "lqip": null}, "view_count": 0, "like_count": 0, "created_at": ""}, {"slug": "未来赛博朋克创意领袖海报-6_e0eab6", "title_zh": "未来赛博朋克创意领袖海报", "title_en": "未来赛博朋克创意领袖海报", "category_slug": "graphic_design", "category_name_zh": "平面设计", "tags": ["poster", "tech-scifi", "creative-play", "graphic-design"], "primary_image": {"r2AccountId": null, "r2Key": null, "remoteUrl": "https://cms-assets.youmind.com/media/1780307034535_jx1820_HJrBTsSbcAAJtLQ.jpg", "width": null, "height": null, "lqip": null}, "view_count": 0, "like_count": 0, "created_at": ""}, {"slug": "古风武侠细腻皮肤-全身照片-神秘梦幻-7_330da8", "title_zh": "古风武侠细腻皮肤、全身照片、神秘梦幻", "title_en": "古风武侠细腻皮肤、全身照片、神秘梦幻", "category_slug": "novel_story", "category_name_zh": "小说推文", "tags": ["novel"], "primary_image": {"r2AccountId": null, "r2Key": null, "remoteUrl": "https://liblibai-online.liblib.cloud/community-img/791137698-39e7e47f0b5ef9323ad0f3274d12c7044021a05ac0ff37b74a42fa0c4e78c4b8.png", "width": null, "height": null, "lqip": null}, "view_count": 0, "like_count": 0, "created_at": ""}, {"slug": "liblib-建筑及室内设计-31e0d22b-1_876998", "title_zh": "Liblib 建筑及室内设计 31e0d22b", "title_en": "Liblib 建筑及室内设计 31e0d22b", "category_slug": "architecture_interior", "category_name_zh": "建筑室内", "tags": ["architecture"], "primary_image": {"r2AccountId": null, "r2Key": null, "remoteUrl": "https://liblibai-online.liblib.cloud/img/58dc75fb35cb48248910891f1e6094b9/3ac68412725fe5b990d02118ea580df9ae6522e3f8ed3649c0b9dd59ce778002.png", "width": null, "height": null, "lqip": null}, "view_count": 0, "like_count": 0, "created_at": ""}, {"slug": "实验性拉面排名海报-8_c7560a", "title_zh": "实验性拉面排名海报", "title_en": "实验性拉面排名海报", "category_slug": "graphic_design", "category_name_zh": "平面设计", "tags": ["poster", "graphic-design"], "primary_image": {"r2AccountId": null, "r2Key": null, "remoteUrl": "https://cms-assets.youmind.com/media/1778230118866_f8425c_HHsJ2EcbQAAhOVs.jpg", "width": null, "height": null, "lqip": null}, "view_count": 0, "like_count": 0, "created_at": ""}, {"slug": "帅气的样子-a_6f2ded", "title_zh": "帅气的样子", "title_en": "帅气的样子", "category_slug": "graphic_design", "category_name_zh": "平面设计", "tags": ["graphic-design"], "primary_image": {"r2AccountId": null, "r2Key": null, "remoteUrl": "https://liblibai-online.liblib.cloud/img/745e1de4f491455cbf7a200159ff2196/fdc78e0b-6f5a-4609-8bf2-dce8a193ddba.png", "width": null, "height": null, "lqip": null}, "view_count": 0, "like_count": 0, "created_at": ""}, {"slug": "文创周边-延展设计-5_8b4e27", "title_zh": "文创周边 延展设计", "title_en": "文创周边 延展设计", "category_slug": "cultural_products", "category_name_zh": "文创周边", "tags": ["cultural-goods", "graphic-design"], "primary_image": {"r2AccountId": null, "r2Key": null, "remoteUrl": "https://liblibai-online.liblib.cloud/community-img/genius_playground/image/b0c8d44bb5934eeebc55948e59368c4e/2bab27ca5e759824e98440cdc1c85dfdfc242a9bc7298fd1005a85660fdcccae.png", "width": null, "height": null, "lqip": null}, "view_count": 0, "like_count": 0, "created_at": ""}, {"slug": "护肤品落地页模型-8_142806", "title_zh": "护肤品落地页模型", "title_en": "护肤品落地页模型", "category_slug": "other", "category_name_zh": "其他", "tags": ["other"], "primary_image": {"r2AccountId": null, "r2Key": null, "remoteUrl": "https://cms-assets.youmind.com/media/1776756819486_rc90vy_HGV6HyHaUAA68FT.jpg", "width": null, "height": null, "lqip": null}, "view_count": 0, "like_count": 0, "created_at": ""}, {"slug": "玩手机可以提神醒脑-物理-1_091df0", "title_zh": "玩手机可以提神醒脑（物理）", "title_en": "玩手机可以提神醒脑（物理）", "category_slug": "sfw", "category_name_zh": "SFW", "tags": ["anime", "二次元", "通用"], "primary_image": {"r2AccountId": null, "r2Key": null, "remoteUrl": "https://files.catbox.moe/73iyvk.png", "width": null, "height": null, "lqip": null}, "view_count": 0, "like_count": 0, "created_at": ""}, {"slug": "未来感-audi-tron-概念轿跑-7_b76b94", "title_zh": "未来感 Audi Tron 概念轿跑", "title_en": "未来感 Audi Tron 概念轿跑", "category_slug": "other", "category_name_zh": "其他", "tags": ["other"], "primary_image": {"r2AccountId": null, "r2Key": null, "remoteUrl": "https://cms-assets.youmind.com/media/1777022600748_ct0tjp_HGlM_ioWMAAL7DO.jpg", "width": null, "height": null, "lqip": null}, "view_count": 0, "like_count": 0, "created_at": ""}, {"slug": "liblib-动漫游戏-c8a0011f-1_1ea774", "title_zh": "Liblib 动漫游戏 c8a0011f", "title_en": "Liblib 动漫游戏 c8a0011f", "category_slug": "anime_game", "category_name_zh": "动漫游戏", "tags": ["anime", "fantasy"], "primary_image": {"r2AccountId": null, "r2Key": null, "remoteUrl": "https://liblibai-online.liblib.cloud/img/a592d854f3fe4ed0819692a94da40120/6693719e-78d4-4cf1-9158-126d56625ccd.png", "width": null, "height": null, "lqip": null}, "view_count": 0, "like_count": 0, "created_at": ""}, {"slug": "黑金山水-蓝金山水-红金山水-b_322217", "title_zh": "黑金山水，蓝金山水，红金山水", "title_en": "黑金山水，蓝金山水，红金山水", "category_slug": "graphic_design", "category_name_zh": "平面设计", "tags": ["graphic-design"], "primary_image": {"r2AccountId": null, "r2Key": null, "remoteUrl": "https://liblibai-online.liblib.cloud/community-img/273049924-8c49a2a4189256cba481ea4eaf0610c55951a21eda22b02057fa0e12c08b89de.png", "width": null, "height": null, "lqip": null}, "view_count": 0, "like_count": 0, "created_at": ""}, {"slug": "可爱的猫咪自拍-4_711bb7", "title_zh": "可爱的猫咪自拍", "title_en": "可爱的猫咪自拍", "category_slug": "other", "category_name_zh": "其他", "tags": ["other"], "primary_image": {"r2AccountId": null, "r2Key": null, "remoteUrl": "https://cms-assets.youmind.com/media/1777280760338_witphb_HG1-l98bQAAD2Of.jpg", "width": null, "height": null, "lqip": null}, "view_count": 0, "like_count": 0, "created_at": ""}, {"slug": "liblib-风格插画-999a2ab6-3_3dded6", "title_zh": "Liblib 风格插画 999a2ab6", "title_en": "Liblib 风格插画 999a2ab6", "category_slug": "illustration", "category_name_zh": "风格插画", "tags": ["illustration"], "primary_image": {"r2AccountId": null, "r2Key": null, "remoteUrl": "https://liblibai-online.liblib.cloud/community-img/793667426-567775ed0e81a4316e59e455c61557035c86eefc02ba9957aa5c09f499e67ca4.png", "width": null, "height": null, "lqip": null}, "view_count": 0, "like_count": 0, "created_at": ""}, {"slug": "咖啡馆窗前的沉思女子与数学公式-2_2eae48", "title_zh": "咖啡馆窗前的沉思女子与数学公式", "title_en": "咖啡馆窗前的沉思女子与数学公式", "category_slug": "other", "category_name_zh": "其他", "tags": ["other"], "primary_image": {"r2AccountId": null, "r2Key": null, "remoteUrl": "https://cms-assets.youmind.com/media/1778748584522_55xfrv_HIQ5IdKaYAAG-H9.jpg", "width": null, "height": null, "lqip": null}, "view_count": 0, "like_count": 0, "created_at": ""}, {"slug": "奢华极简主义日式艺术肖像-8_82a526", "title_zh": "奢华极简主义日式艺术肖像", "title_en": "奢华极简主义日式艺术肖像", "category_slug": "photography", "category_name_zh": "摄影写真", "tags": ["photography", "portrait"], "primary_image": {"r2AccountId": null, "r2Key": null, "remoteUrl": "https://cms-assets.youmind.com/media/1780217246351_2t8alu_HJkISzQawAAPkc7.jpg", "width": null, "height": null, "lqip": null}, "view_count": 0, "like_count": 0, "created_at": ""}, {"slug": "青水奥义-8_1ac91b", "title_zh": "青水奥义", "title_en": "青水奥义", "category_slug": "sfw", "category_name_zh": "SFW", "tags": ["anime", "二次元", "通用", "游戏"], "primary_image": {"r2AccountId": null, "r2Key": null, "remoteUrl": "https://files.catbox.moe/e55qri.png", "width": null, "height": null, "lqip": null}, "view_count": 0, "like_count": 0, "created_at": ""}, {"slug": "橄榄绿t恤-高级感影棚人像摄影提示词-3_276653", "title_zh": "橄榄绿T恤·高级感影棚人像摄影提示词", "title_en": "橄榄绿T恤·高级感影棚人像摄影提示词", "category_slug": "photography", "category_name_zh": "摄影写真", "tags": ["时尚肖像", "photography", "fashion", "影棚布光", "portrait"], "primary_image": {"r2AccountId": null, "r2Key": null, "remoteUrl": "https://static.prompthub.xin/uploads/prompts/1777187481836-bf4beea24e6a2e01b03a982740ad8ec8_detail.jpg?auth_key=1777949834-0-0-4780cbfe1227debc31324718df4c0522", "width": null, "height": null, "lqip": null}, "view_count": 0, "like_count": 0, "created_at": ""}, {"slug": "cg手绘厚涂插画人像-v1-至臻美人光影-月下美人-e_ea643f", "title_zh": "CG手绘厚涂插画人像-V1-至臻美人光影-月下美人", "title_en": "CG手绘厚涂插画人像-V1-至臻美人光影-月下美人", "category_slug": "illustration", "category_name_zh": "风格插画", "tags": ["illustration", "portrait"], "primary_image": {"r2AccountId": null, "r2Key": null, "remoteUrl": "https://liblibai-online.liblib.cloud/img/ea845bc2267c4c1aa6df5099a6da594c/5d9f1a7a-a4c9-4cbc-943f-a282e45b6d56.png", "width": null, "height": null, "lqip": null}, "view_count": 0, "like_count": 0, "created_at": ""}]