{"items": [{"id": "ee92fb7c-00cd-4f50-a0c2-b1a592b40b21", "slug": "f-1-industrial-product-design-2_2f32ca", "title": {"en": "F.1 Industrial Product Design", "zh": "F.1 Industrial Product Design"}, "category": {"id": "e71e276b-32f8-45c9-b1c3-a578ac8585a1", "slug": "architecture_interior", "name": {"en": "建筑室内", "zh": "建筑室内"}}, "tags": [{"slug": "architecture", "name": {"en": "Architecture", "zh": "建筑空间"}}], "primaryImage": {"r2AccountId": null, "r2Key": null, "remoteUrl": "https://liblibai-online.liblib.cloud/img/be68882bf7db496681829add0b5d1ed0/eb37ac4da157b9d3f09141bd2fe42e70cfee06e6d45518db1cf24210c9dfc7a5.png", "width": null, "height": null, "lqip": null}, "viewCount": 0, "likeCount": 0, "sourceSite": "Liblib Inspiration"}, {"id": "7001d272-6545-4e38-ad1a-00158630ccec", "slug": "最后的晚餐-壁画高清修复照片-4_f0b4d2", "title": {"en": "《最后的晚餐》壁画高清修复照片", "zh": "《最后的晚餐》壁画高清修复照片"}, "category": {"id": "59e873d5-c26f-4011-8a5f-caf98cc5b0d1", "slug": "photography", "name": {"en": "摄影写真", "zh": "摄影写真"}}, "tags": [{"slug": "photography", "name": {"en": "Photography", "zh": "摄影"}}], "primaryImage": {"r2AccountId": null, "r2Key": null, "remoteUrl": "https://cms-assets.youmind.com/media/1777193383143_c1mde1_HGwEsFgakAEB02f.jpg", "width": null, "height": null, "lqip": null}, "viewCount": 0, "likeCount": 0, "sourceSite": "YouMind GPT Image 2 Prompts"}, {"id": "c81887ab-8370-4474-babd-dc2331b67ef2", "slug": "liblib-建筑及室内设计-391f692a-b_a90027", "title": {"en": "Liblib 建筑及室内设计 391f692a", "zh": "Liblib 建筑及室内设计 391f692a"}, "category": {"id": "e71e276b-32f8-45c9-b1c3-a578ac8585a1", "slug": "architecture_interior", "name": {"en": "建筑室内", "zh": "建筑室内"}}, "tags": [{"slug": "architecture", "name": {"en": "Architecture", "zh": "建筑空间"}}], "primaryImage": {"r2AccountId": null, "r2Key": null, "remoteUrl": "https://liblibai-online.liblib.cloud/community-img/560b875866bcffeaded9e2532c07361a781631ffdd9f009cc3781d103bb3624e.png", "width": null, "height": null, "lqip": null}, "viewCount": 0, "likeCount": 0, "sourceSite": "Liblib Inspiration"}, {"id": "b12a2a88-b984-46fe-a3e3-74da1cd7a62d", "slug": "化妆品场景图-1_380833", "title": {"en": "化妆品场景图", "zh": "化妆品场景图"}, "category": {"id": "ea38cbdf-1214-4cfa-9432-f3def03a838c", "slug": "ecommerce", "name": {"en": "电商营销", "zh": "电商营销"}}, "tags": [{"slug": "product", "name": {"en": "Product", "zh": "产品"}}, {"slug": "ecommerce", "name": {"en": "E-commerce", "zh": "电商营销"}}], "primaryImage": {"r2AccountId": null, "r2Key": null, "remoteUrl": "https://liblibai-online.liblib.cloud/img/50d2d573397548229b37334d77ffcc28/3edf5c6b213ba56783616be191a149d985804d1690af35dddae14f14b65c626e.png", "width": null, "height": null, "lqip": null}, "viewCount": 0, "likeCount": 0, "sourceSite": "Liblib Inspiration"}, {"id": "7645c4e0-36fd-4026-b77f-588240d38f0d", "slug": "产品结构特效-5_00f387", "title": {"en": "产品结构特效", "zh": "产品结构特效"}, "category": {"id": "e71e276b-32f8-45c9-b1c3-a578ac8585a1", "slug": "architecture_interior", "name": {"en": "建筑室内", "zh": "建筑室内"}}, "tags": [{"slug": "architecture", "name": {"en": "Architecture", "zh": "建筑空间"}}, {"slug": "product", "name": {"en": "Product", "zh": "产品"}}], "primaryImage": {"r2AccountId": null, "r2Key": null, "remoteUrl": "https://liblibai-online.liblib.cloud/img/21166b89a24e4097adf013bd0ebf9e39/743690ad305ec704f55e5b5fb98d4814d7baf19d768b2c896cb3eb029fa31692.png", "width": null, "height": null, "lqip": null}, "viewCount": 0, "likeCount": 0, "sourceSite": "Liblib Inspiration"}, {"id": "643beb26-0f3e-4fb6-9518-f0271907e360", "slug": "4-4-动作分解参考表-9_28d912", "title": {"en": "4×4 动作分解参考表", "zh": "4×4 动作分解参考表"}, "category": {"id": "ea38cbdf-1214-4cfa-9432-f3def03a838c", "slug": "ecommerce", "name": {"en": "电商营销", "zh": "电商营销"}}, "tags": [{"slug": "character", "name": {"en": "Character", "zh": "角色人物"}}, {"slug": "illustration", "name": {"en": "Illustration", "zh": "插画"}}, {"slug": "anime", "name": {"en": "Anime & Game", "zh": "动漫游戏"}}, {"slug": "poster", "name": {"en": "Poster", "zh": "海报"}}, {"slug": "infographic", "name": {"en": "Infographic", "zh": "信息图"}}, {"slug": "tech-scifi", "name": {"en": "Tech & Sci-Fi", "zh": "科技科幻"}}, {"slug": "ecommerce", "name": {"en": "E-commerce", "zh": "电商营销"}}], "primaryImage": {"r2AccountId": null, "r2Key": null, "remoteUrl": "https://gpt-image2.canghe.ai/images/case347.jpg", "width": null, "height": null, "lqip": null}, "viewCount": 0, "likeCount": 0, "sourceSite": "AI2Image GPT Image 2 分类页"}, {"id": "a02e7d2e-885f-43ec-90de-c0ff21ee8067", "slug": "小猫怼脸拍-b_ba5206", "title": {"en": "小猫怼脸拍", "zh": "小猫怼脸拍"}, "category": {"id": "e71e276b-32f8-45c9-b1c3-a578ac8585a1", "slug": "architecture_interior", "name": {"en": "建筑室内", "zh": "建筑室内"}}, "tags": [{"slug": "architecture", "name": {"en": "Architecture", "zh": "建筑空间"}}, {"slug": "product", "name": {"en": "Product", "zh": "产品"}}, {"slug": "landscape", "name": {"en": "Landscape", "zh": "风景场景"}}, {"slug": "animal", "name": {"en": "Animal", "zh": "动物"}}, {"slug": "photography", "name": {"en": "Photography", "zh": "摄影"}}], "primaryImage": {"r2AccountId": null, "r2Key": null, "remoteUrl": "https://liblibai-online.liblib.cloud/img/025e5a1b90a14812b9b099de95da8698/7715454e-f727-4f69-9ee2-242309c89c90.png", "width": null, "height": null, "lqip": null}, "viewCount": 0, "likeCount": 0, "sourceSite": "Liblib Inspiration"}, {"id": "444063ed-c93d-42e0-9ed9-d448a479e852", "slug": "黄金时刻咖啡馆人像-电影感街拍提示词-2_ef4925", "title": {"en": "黄金时刻咖啡馆人像 | 电影感街拍提示词", "zh": "黄金时刻咖啡馆人像 | 电影感街拍提示词"}, "category": {"id": "59e873d5-c26f-4011-8a5f-caf98cc5b0d1", "slug": "photography", "name": {"en": "摄影写真", "zh": "摄影写真"}}, "tags": [{"slug": "cinematic", "name": {"en": "Cinematic", "zh": "电影感"}}, {"slug": "咖啡馆街拍", "name": {"en": "咖啡馆街拍", "zh": "咖啡馆街拍"}}, {"slug": "photography", "name": {"en": "Photography", "zh": "摄影"}}, {"slug": "fashion", "name": {"en": "Fashion", "zh": "时尚"}}, {"slug": "黄金时刻", "name": {"en": "黄金时刻", "zh": "黄金时刻"}}, {"slug": "portrait", "name": {"en": "Portrait", "zh": "人像"}}], "primaryImage": {"r2AccountId": null, "r2Key": null, "remoteUrl": "https://static.prompthub.xin/uploads/prompts/1777310134168-133016cdcb30ec2f99aad96af4493eb6_detail.jpg?auth_key=1777949709-0-0-dc5f6e109f0e20fae02d23a317a5e430", "width": null, "height": null, "lqip": null}, "viewCount": 0, "likeCount": 0, "sourceSite": "AI2Image GPT Image 2 分类页"}, {"id": "163c70bb-1cc4-4801-b453-38dce235210d", "slug": "liblib-风格插画-84a33074-7_7d395f", "title": {"en": "Liblib 风格插画 84a33074", "zh": "Liblib 风格插画 84a33074"}, "category": {"id": "a0141b5e-1ffc-4d1d-ad28-1a33a597707c", "slug": "illustration", "name": {"en": "风格插画", "zh": "风格插画"}}, "tags": [{"slug": "illustration", "name": {"en": "Illustration", "zh": "插画"}}], "primaryImage": {"r2AccountId": null, "r2Key": null, "remoteUrl": "https://liblibai-online.liblib.cloud/community-img/7983672c563fb7a87ea224d7964ab38d4d2a290175728d9db115c7426849bc25.png", "width": null, "height": null, "lqip": null}, "viewCount": 0, "likeCount": 0, "sourceSite": "Liblib Inspiration"}, {"id": "792f6b46-48c3-4e2a-ac3d-3b9f76e2ee89", "slug": "liblib-建筑及室内设计-18886fcb-2_86e49d", "title": {"en": "Liblib 建筑及室内设计 18886fcb", "zh": "Liblib 建筑及室内设计 18886fcb"}, "category": {"id": "e71e276b-32f8-45c9-b1c3-a578ac8585a1", "slug": "architecture_interior", "name": {"en": "建筑室内", "zh": "建筑室内"}}, "tags": [{"slug": "architecture", "name": {"en": "Architecture", "zh": "建筑空间"}}], "primaryImage": {"r2AccountId": null, "r2Key": null, "remoteUrl": "https://liblibai-online.liblib.cloud/community-img/35f81eb3999286247aa6472113193ea4b4dee3a783d3808aa5a23dc0b490c597.png", "width": null, "height": null, "lqip": null}, "viewCount": 0, "likeCount": 0, "sourceSite": "Liblib Inspiration"}, {"id": "207fff02-ccd0-453f-ac38-de443006d4bd", "slug": "现场摇滚音乐会海报-3_5ce632", "title": {"en": "现场摇滚音乐会海报", "zh": "现场摇滚音乐会海报"}, "category": {"id": "76d93b93-00b9-4318-8dfd-27e94c62d797", "slug": "graphic_design", "name": {"en": "平面设计", "zh": "平面设计"}}, "tags": [{"slug": "poster", "name": {"en": "Poster", "zh": "海报"}}, {"slug": "graphic-design", "name": {"en": "Graphic Design", "zh": "平面设计"}}], "primaryImage": {"r2AccountId": null, "r2Key": null, "remoteUrl": "https://cms-assets.youmind.com/media/1778921864216_u4eg94_HIV5CJYXgAA4qgx.jpg", "width": null, "height": null, "lqip": null}, "viewCount": 0, "likeCount": 0, "sourceSite": "YouMind GPT Image 2 Prompts"}, {"id": "f8cf3dac-df78-43e6-b22f-3cc5da817a82", "slug": "雨姐带派大脚图-8_f59dc0", "title": {"en": "雨姐带派大脚图", "zh": "雨姐带派大脚图"}, "category": {"id": "f3287862-afbd-4042-bab4-216576cadf44", "slug": "sfw", "name": {"en": "SFW", "zh": "SFW"}}, "tags": [{"slug": "anime", "name": {"en": "Anime & Game", "zh": "动漫游戏"}}, {"slug": "二次元", "name": {"en": "二次元", "zh": "二次元"}}, {"slug": "通用", "name": {"en": "通用", "zh": "通用"}}], "primaryImage": {"r2AccountId": null, "r2Key": null, "remoteUrl": "https://files.catbox.moe/n71izl.jpg", "width": null, "height": null, "lqip": null}, "viewCount": 0, "likeCount": 0, "sourceSite": "Nanobanana Website Vercel"}, {"id": "4a4ccad8-bcfd-4a76-a10b-9c210bde93d1", "slug": "liblib-平面设计-cc819bfa-e_82c456", "title": {"en": "Liblib 平面设计 cc819bfa", "zh": "Liblib 平面设计 cc819bfa"}, "category": {"id": "76d93b93-00b9-4318-8dfd-27e94c62d797", "slug": "graphic_design", "name": {"en": "平面设计", "zh": "平面设计"}}, "tags": [{"slug": "graphic-design", "name": {"en": "Graphic Design", "zh": "平面设计"}}], "primaryImage": {"r2AccountId": null, "r2Key": null, "remoteUrl": "https://liblibai-online.liblib.cloud/community-img/27861f5ea3a6b85422e55a1384382b34c899f96b1c9030a0ab9fc0fe9fb24913.png", "width": null, "height": null, "lqip": null}, "viewCount": 0, "likeCount": 0, "sourceSite": "Liblib Inspiration"}, {"id": "d2a06283-900d-4d3b-a5e9-9230d7620290", "slug": "信息图可视化设计-6_b5e5f1", "title": {"en": "信息图可视化设计", "zh": "信息图可视化设计"}, "category": {"id": "76d93b93-00b9-4318-8dfd-27e94c62d797", "slug": "graphic_design", "name": {"en": "平面设计", "zh": "平面设计"}}, "tags": [{"slug": "character", "name": {"en": "Character", "zh": "角色人物"}}, {"slug": "infographic", "name": {"en": "Infographic", "zh": "信息图"}}, {"slug": "novel", "name": {"en": "Novel & Story", "zh": "小说推文"}}, {"slug": "tech-scifi", "name": {"en": "Tech & Sci-Fi", "zh": "科技科幻"}}, {"slug": "tech", "name": {"en": "Tech", "zh": "Tech"}}, {"slug": "graphic-design", "name": {"en": "Graphic Design", "zh": "平面设计"}}, {"slug": "ui", "name": {"en": "UI", "zh": "UI 界面"}}], "primaryImage": {"r2AccountId": null, "r2Key": null, "remoteUrl": "https://gpt-image2.canghe.ai/images/case270.jpg", "width": null, "height": null, "lqip": null}, "viewCount": 0, "likeCount": 0, "sourceSite": "AI2Image GPT Image 2 分类页"}, {"id": "ee85c243-34fe-4815-a815-d609c0481570", "slug": "美漫星际科幻末日废土室内场景-3_d7763d", "title": {"en": "美漫星际科幻末日废土室内场景", "zh": "美漫星际科幻末日废土室内场景"}, "category": {"id": "e71e276b-32f8-45c9-b1c3-a578ac8585a1", "slug": "architecture_interior", "name": {"en": "建筑室内", "zh": "建筑室内"}}, "tags": [{"slug": "architecture", "name": {"en": "Architecture", "zh": "建筑空间"}}, {"slug": "tech-scifi", "name": {"en": "Tech & Sci-Fi", "zh": "科技科幻"}}], "primaryImage": {"r2AccountId": null, "r2Key": null, "remoteUrl": "https://liblibai-online.liblib.cloud/img/97fbfc972ac1409a98236cff5125da66/149bf11e6fb177f108e93c7d04cac7dda371d1a12c6620aecaa2b355b64610aa.png", "width": null, "height": null, "lqip": null}, "viewCount": 0, "likeCount": 0, "sourceSite": "Liblib Inspiration"}, {"id": "8c96d7a6-bfcc-45c5-814f-ab80cdf08a22", "slug": "复古尼崎市旅游海报-3_887532", "title": {"en": "复古尼崎市旅游海报", "zh": "复古尼崎市旅游海报"}, "category": {"id": "76d93b93-00b9-4318-8dfd-27e94c62d797", "slug": "graphic_design", "name": {"en": "平面设计", "zh": "平面设计"}}, "tags": [{"slug": "poster", "name": {"en": "Poster", "zh": "海报"}}, {"slug": "graphic-design", "name": {"en": "Graphic Design", "zh": "平面设计"}}], "primaryImage": {"r2AccountId": null, "r2Key": null, "remoteUrl": "https://cms-assets.youmind.com/media/1779959582446_h4ko98_HJUSi2iaAAA9LsN.jpg", "width": null, "height": null, "lqip": null}, "viewCount": 0, "likeCount": 0, "sourceSite": "YouMind GPT Image 2 Prompts"}, {"id": "5d6570df-9418-4937-931a-4cbfdd997a7c", "slug": "蓝鸟队-blue-jays-广播观众镜头-3_a9f9ad", "title": {"en": "蓝鸟队 (Blue Jays) 广播观众镜头", "zh": "蓝鸟队 (Blue Jays) 广播观众镜头"}, "category": {"id": "6f7e386d-b023-410d-9805-cf8165be9a78", "slug": "other", "name": {"en": "其他", "zh": "其他"}}, "tags": [{"slug": "other", "name": {"en": "Other", "zh": "其他"}}], "primaryImage": {"r2AccountId": null, "r2Key": null, "remoteUrl": "https://cms-assets.youmind.com/media/1778662270045_dcp5vk_HIGEG6KXgAAYM7a.jpg", "width": null, "height": null, "lqip": null}, "viewCount": 0, "likeCount": 0, "sourceSite": "YouMind GPT Image 2 Prompts"}, {"id": "a4739314-ccc9-4ea0-8237-1eae46be16df", "slug": "机械月下的英雄-4_d7b32e", "title": {"en": "机械月下的英雄", "zh": "机械月下的英雄"}, "category": {"id": "6f7e386d-b023-410d-9805-cf8165be9a78", "slug": "other", "name": {"en": "其他", "zh": "其他"}}, "tags": [{"slug": "other", "name": {"en": "Other", "zh": "其他"}}], "primaryImage": {"r2AccountId": null, "r2Key": null, "remoteUrl": "https://cms-assets.youmind.com/media/1778921936747_ne29fe_HIZHI3kXYAAUu_1.jpg", "width": null, "height": null, "lqip": null}, "viewCount": 0, "likeCount": 0, "sourceSite": "YouMind GPT Image 2 Prompts"}, {"id": "9f4555d8-14a3-46d2-a046-88a1302e5d5f", "slug": "一键生成电商详情页全案长图-高转化策划案-上传产品即可-b_e04a8a", "title": {"en": "一键生成电商详情页全案长图｜高转化策划案｜上传产品即可", "zh": "一键生成电商详情页全案长图｜高转化策划案｜上传产品即可"}, "category": {"id": "ea38cbdf-1214-4cfa-9432-f3def03a838c", "slug": "ecommerce", "name": {"en": "电商营销", "zh": "电商营销"}}, "tags": [{"slug": "product", "name": {"en": "Product", "zh": "产品"}}, {"slug": "ecommerce", "name": {"en": "E-commerce", "zh": "电商营销"}}], "primaryImage": {"r2AccountId": null, "r2Key": null, "remoteUrl": "https://liblibai-online.liblib.cloud/community-img/genius_playground/image/ea845bc2267c4c1aa6df5099a6da594c/e93a67072f79975f849bea3ff6b0cfaf0abc1398592c9d6998de012e3e448df4.png", "width": null, "height": null, "lqip": null}, "viewCount": 0, "likeCount": 0, "sourceSite": "Liblib Inspiration"}, {"id": "79fbdc82-554a-4706-b7e2-594515c9efa6", "slug": "liblib-建筑及室内设计-e88d6118-e_52f69d", "title": {"en": "Liblib 建筑及室内设计 e88d6118", "zh": "Liblib 建筑及室内设计 e88d6118"}, "category": {"id": "e71e276b-32f8-45c9-b1c3-a578ac8585a1", "slug": "architecture_interior", "name": {"en": "建筑室内", "zh": "建筑室内"}}, "tags": [{"slug": "architecture", "name": {"en": "Architecture", "zh": "建筑空间"}}], "primaryImage": {"r2AccountId": null, "r2Key": null, "remoteUrl": "https://liblibai-online.liblib.cloud/community-img/4f3f68d64dd78ae1f3bf5d14fecfee8a3c03f0786488344d6f719c9bc0218f87.png", "width": null, "height": null, "lqip": null}, "viewCount": 0, "likeCount": 0, "sourceSite": "Liblib Inspiration"}], "has_more": true}